torch_kmeans/__init__.py
torch_kmeans/clustering/__init__.py
torch_kmeans/clustering/constr_kmeans.py
torch_kmeans/clustering/kmeans.py
torch_kmeans/clustering/knn.py
torch_kmeans/clustering/soft_kmeans.py
torch_kmeans/utils/__init__.py
torch_kmeans/utils/distances.py
torch_kmeans/utils/utils.py
torch_kmeans-0.2.0.dist-info/LICENSE.txt
torch_kmeans-0.2.0.dist-info/METADATA
torch_kmeans-0.2.0.dist-info/WHEEL
torch_kmeans-0.2.0.dist-info/top_level.txt
torch_kmeans-0.2.0.dist-info/RECORD
