Metadata-Version: 2.1
Name: torch-kmeans
Version: 0.2.0
Summary: PyTorch implementations of KMeans, Soft-KMeans and Constrained-KMeans which can be run on GPU and work on (mini-)batches of data.
Home-page: https://github.com/jokofa/torch_kmeans
Author: Jonas K. Falkner
Author-email: jokofa@gmail.com
License: MIT
Project-URL: Documentation, https://readthedocs.org/
Platform: any
Classifier: Development Status :: 4 - Beta
Classifier: Programming Language :: Python
Classifier: License :: OSI Approved :: MIT License
Classifier: Intended Audience :: Developers
Classifier: Intended Audience :: Science/Research
Classifier: Programming Language :: Python :: 3
Classifier: Programming Language :: Python :: 3.6
Classifier: Programming Language :: Python :: 3.7
Classifier: Programming Language :: Python :: 3.8
Classifier: Programming Language :: Python :: 3.9
Classifier: Topic :: Scientific/Engineering :: Artificial Intelligence
Requires-Python: >=3.7
License-File: LICENSE.txt
Requires-Dist: numpy (>=1.18)
Requires-Dist: torch (>=1.08)
Requires-Dist: importlib-metadata ; python_version < "3.8"
Provides-Extra: testing
Requires-Dist: setuptools ; extra == 'testing'
Requires-Dist: pytest ; extra == 'testing'
Requires-Dist: pytest-cov ; extra == 'testing'
Requires-Dist: pre-commit ; extra == 'testing'
Requires-Dist: scikit-learn ; extra == 'testing'
Requires-Dist: sphinx-rtd-theme ; extra == 'testing'
